Metadata-Version: 2.1
Name: pymacaron-google-datastore
Version: 0.0.3
Summary: Serialize/Deserialize Swagger objects to and from Google Firestore in Datastore mode
Home-page: https://github.com/pymacaron/pymacaron-google-datastore
Author: Erwan Lemonnier
Author-email: erwan@lemonnier.se
License: BSD
Platform: any
Classifier: Environment :: Web Environment
Classifier: Intended Audience :: Developers
Classifier: License :: OSI Approved :: BSD License
Classifier: Operating System :: OS Independent
Classifier: Programming Language :: Python
Classifier: Topic :: Internet :: WWW/HTTP :: Dynamic Content
Classifier: Topic :: Software Development :: Libraries :: Python Modules
